odoo10_addon_sale_crm_operating_unit-10.0.1.0.0.99.dev2-py2.7-nspkg.pth
odoo/addons/sale_crm_operating_unit/README.rst
odoo/addons/sale_crm_operating_unit/__init__.py
odoo/addons/sale_crm_operating_unit/__manifest__.py
odoo/addons/sale_crm_operating_unit/models/__init__.py
odoo/addons/sale_crm_operating_unit/models/sale.py
odoo/addons/sale_crm_operating_unit/static/description/icon.png
odoo/addons/sale_crm_operating_unit/tests/__init__.py
odoo/addons/sale_crm_operating_unit/tests/test_sale_crm_operating_unit.py
odoo/addons/sale_crm_operating_unit/views/sale_crm_view.xml
odoo10_addon_sale_crm_operating_unit-10.0.1.0.0.99.dev2.dist-info/DESCRIPTION.rst
odoo10_addon_sale_crm_operating_unit-10.0.1.0.0.99.dev2.dist-info/METADATA
odoo10_addon_sale_crm_operating_unit-10.0.1.0.0.99.dev2.dist-info/RECORD
odoo10_addon_sale_crm_operating_unit-10.0.1.0.0.99.dev2.dist-info/WHEEL
odoo10_addon_sale_crm_operating_unit-10.0.1.0.0.99.dev2.dist-info/metadata.json
odoo10_addon_sale_crm_operating_unit-10.0.1.0.0.99.dev2.dist-info/namespace_packages.txt
odoo10_addon_sale_crm_operating_unit-10.0.1.0.0.99.dev2.dist-info/top_level.txt
