Metadata-Version: 2.0
Name: odoo10-addon-sale-crm-operating-unit
Version: 10.0.1.0.0.99.dev2
Summary: Sale CRM Operating Unit
Home-page: https://odoo-community.org/
Author: Eficent Business and IT Consulting Services S.L., Serpent Consulting Services Pvt. Ltd.,Odoo Community Association (OCA)
Author-email: support@odoo-community.org
License: LGPL-3
Platform: UNKNOWN
Classifier: Programming Language :: Python
Classifier: Framework :: Odoo
Classifier: License :: OSI Approved :: GNU Lesser General Public License v3 (LGPLv3)
Requires-Python: ~=2.7
Requires-Dist: odoo (<10.1dev,>=10.0)
Requires-Dist: odoo10-addon-base-view-inheritance-extension
Requires-Dist: odoo10-addon-crm-operating-unit
Requires-Dist: odoo10-addon-sale-operating-unit
